{
  "id": "cicindela_repanda",
  "scientific_name": "Cicindela repanda",
  "common_name": "Bronzed Tiger Beetle",
  "family": "cicindelidae",
  "genus": "cicindela",
  "indiana_status": "confirmed",
  "gbif_taxon_key": 1034720,
  "inat_taxon_id": 82425,
  "diagnosis": "Cicindela repanda, commonly known as the bronzed tiger beetle or common shore tiger beetle, is a species of tiger beetle that measures 10–13 millimetres (0.39–0.51 in) long, lives in most of North America. Its labrum is small with one tooth and the pronotum is coppery and hairy.",
  "body_size_mm": "",
  "diagnostic_characters": [],
  "phenology": [
    3,
    4,
    5,
    6,
    7,
    8,
    9,
    10,
    11
  ],
  "phenology_peak": [
    4,
    8,
    9
  ],
  "counties": [
    "Boone",
    "Brown",
    "Carroll",
    "Clark",
    "Clinton",
    "Crawford",
    "Elkhart",
    "Franklin",
    "Hamilton",
    "Harrison",
    "Jackson",
    "Lake",
    "Martin",
    "Monroe",
    "Morgan",
    "Porter",
    "Posey",
    "Starke",
    "Switzerland",
    "Tippecanoe",
    "Vigo",
    "Warren"
  ],
  "county_record_counts": {
    "Posey": 3,
    "Boone": 12,
    "Porter": 11,
    "Franklin": 2,
    "Tippecanoe": 9,
    "Switzerland": 2,
    "Monroe": 3,
    "Brown": 1,
    "Jackson": 1,
    "Morgan": 1,
    "Carroll": 2,
    "Lake": 5,
    "Martin": 1,
    "Warren": 1,
    "Vigo": 1,
    "Clark": 3,
    "Clinton": 1,
    "Crawford": 1,
    "Elkhart": 1,
    "Hamilton": 1,
    "Harrison": 1,
    "Starke": 4
  },
  "images": [],
  "similar_species": [],
  "references": [
    "Source: Wikipedia, *https://en.wikipedia.org/wiki/Cicindela_repanda*, retrieved 2026-05-26."
  ],
  "last_refreshed": "2026-05-26"
}
