{
  "id": "cicindela_sexguttata",
  "scientific_name": "Cicindela sexguttata",
  "common_name": "Six-spotted Tiger Beetle",
  "family": "cicindelidae",
  "genus": "cicindela",
  "indiana_status": "confirmed",
  "gbif_taxon_key": 1034887,
  "inat_taxon_id": 49566,
  "diagnosis": "The six-spotted tiger beetle, also known as the six-spotted green tiger beetle (Cicindela sexguttata), is a common North American species of ground beetle in the Cicindelinae subfamily.",
  "body_size_mm": "12–14",
  "diagnostic_characters": [],
  "phenology": [
    1,
    3,
    4,
    5,
    6,
    7,
    8,
    9,
    10,
    11
  ],
  "phenology_peak": [
    4,
    5
  ],
  "counties": [
    "Allen",
    "Boone",
    "Brown",
    "Clark",
    "DeKalb",
    "Elkhart",
    "Fayette",
    "Floyd",
    "Grant",
    "Hamilton",
    "Hancock",
    "Hendricks",
    "Howard",
    "Jennings",
    "Johnson",
    "Kosciusko",
    "Lake",
    "Lawrence",
    "Marion",
    "Miami",
    "Monroe",
    "Montgomery",
    "Morgan",
    "Owen",
    "Porter",
    "Putnam",
    "Scott",
    "Shelby",
    "St. Joseph",
    "Steuben",
    "Tippecanoe",
    "Vanderburgh",
    "Vermillion",
    "Vigo",
    "Warren",
    "Washington",
    "Wayne",
    "White",
    "Whitley"
  ],
  "county_record_counts": {
    "Marion": 69,
    "White": 1,
    "Hamilton": 10,
    "Kosciusko": 1,
    "Allen": 6,
    "Boone": 16,
    "Johnson": 1,
    "Morgan": 1,
    "Tippecanoe": 17,
    "Brown": 4,
    "Montgomery": 2,
    "St. Joseph": 2,
    "DeKalb": 1,
    "Hendricks": 14,
    "Porter": 6,
    "Monroe": 5,
    "Grant": 1,
    "Howard": 2,
    "Clark": 2,
    "Putnam": 3,
    "Warren": 1,
    "Fayette": 6,
    "Owen": 1,
    "Steuben": 2,
    "Lake": 1,
    "Vermillion": 1,
    "Vigo": 1,
    "Elkhart": 1,
    "Washington": 1,
    "Miami": 1,
    "Whitley": 2,
    "Wayne": 4,
    "Floyd": 1,
    "Vanderburgh": 1,
    "Jennings": 2,
    "Shelby": 1,
    "Hancock": 3,
    "Lawrence": 1,
    "Scott": 1
  },
  "images": [],
  "similar_species": [],
  "references": [
    "Source: Wikipedia, *https://en.wikipedia.org/wiki/Cicindela_sexguttata*, retrieved 2026-05-26."
  ],
  "last_refreshed": "2026-05-26"
}
