{
  "id": "platydema_elliptica",
  "scientific_name": "Platydema elliptica",
  "common_name": "Orange-banded Darkling Beetle",
  "family": "tenebrionidae",
  "genus": "platydema",
  "indiana_status": "confirmed",
  "gbif_taxon_key": 8233735,
  "inat_taxon_id": 1160142,
  "diagnosis": "",
  "body_size_mm": "",
  "diagnostic_characters": [],
  "phenology": [
    5,
    9
  ],
  "phenology_peak": [
    5,
    9
  ],
  "counties": [
    "Morgan",
    "Tippecanoe",
    "Vanderburgh"
  ],
  "images": [],
  "similar_species": [],
  "references": [],
  "county_record_counts": {
    "Tippecanoe": 1,
    "Morgan": 1,
    "Vanderburgh": 1
  },
  "last_refreshed": "2026-05-22"
}
