{
  "id": "xylotrechus_colonus",
  "scientific_name": "Xylotrechus colonus",
  "common_name": "Rustic Borer",
  "family": "cerambycidae",
  "genus": "xylotrechus",
  "indiana_status": "confirmed",
  "gbif_taxon_key": 1159031,
  "inat_taxon_id": 233860,
  "diagnosis": "Xylotrechus colonus is a species of beetle in the family Cerambycidae. It was described by Fabricius in 1775.",
  "body_size_mm": "",
  "diagnostic_characters": [],
  "phenology": [
    4,
    5,
    6,
    7,
    8,
    9,
    10
  ],
  "phenology_peak": [
    6,
    7
  ],
  "counties": [
    "Allen",
    "Bartholomew",
    "Boone",
    "Brown",
    "Clay",
    "Dubois",
    "Floyd",
    "Hamilton",
    "Hancock",
    "Henry",
    "Howard",
    "Jennings",
    "Johnson",
    "Lake",
    "LaPorte",
    "Madison",
    "Marion",
    "Monroe",
    "Morgan",
    "Noble",
    "Parke",
    "Perry",
    "Porter",
    "Shelby",
    "St. Joseph",
    "Starke",
    "Tippecanoe",
    "Vanderburgh",
    "Whitley"
  ],
  "images": [],
  "similar_species": [],
  "references": [
    "Source: Wikipedia, *http://en.wikipedia.org/wiki/Xylotrechus_colonus*, retrieved 2026-05-22."
  ],
  "county_record_counts": {
    "Hamilton": 6,
    "Allen": 8,
    "Morgan": 5,
    "Bartholomew": 2,
    "Noble": 2,
    "St. Joseph": 4,
    "Jennings": 1,
    "Howard": 1,
    "Parke": 2,
    "Whitley": 1,
    "Clay": 1,
    "Monroe": 11,
    "Floyd": 1,
    "Johnson": 2,
    "Marion": 1,
    "Lake": 5,
    "Brown": 2,
    "Boone": 1,
    "Madison": 2,
    "Hancock": 1,
    "Starke": 3,
    "Dubois": 1,
    "Shelby": 1,
    "Porter": 2,
    "Henry": 1,
    "Vanderburgh": 1,
    "Perry": 1,
    "LaPorte": 1,
    "Tippecanoe": 1
  },
  "last_refreshed": "2026-05-22"
}
