{
  "id": "bothrideridae",
  "name": "Bothrideridae",
  "common_name": "Dry Bark Beetles",
  "authority": "",
  "diagnosis": "Bothrideridae is a family of beetles in the suborder Polyphaga. They are known commonly as the cocoon-forming beetles or dry bark beetles. They occur worldwide with most native to the Old World tropics.",
  "species_count": 0,
  "genus_count": 0,
  "confirmed_count": null,
  "historical_count": null,
  "adventive_count": null,
  "inat_taxon_id": 173345,
  "genus_notes": {}
}
